csvbase_client/VERSION
csvbase_client/__init__.py
csvbase_client/constants.py
csvbase_client/exceptions.py
csvbase_client/fsspec.py
csvbase_client/io.py
csvbase_client/internals/__init__.py
csvbase_client/internals/auth.py
csvbase_client/internals/cache.py
csvbase_client/internals/cli.py
csvbase_client/internals/config.py
csvbase_client/internals/dirs.py
csvbase_client/internals/http.py
csvbase_client/internals/value_objs.py
csvbase_client/internals/version.py
csvbase_client-0.1.1.dist-info/COPYING
csvbase_client-0.1.1.dist-info/METADATA
csvbase_client-0.1.1.dist-info/WHEEL
csvbase_client-0.1.1.dist-info/entry_points.txt
csvbase_client-0.1.1.dist-info/top_level.txt
csvbase_client-0.1.1.dist-info/RECORD
