Metadata-Version: 2.1
Name: csvbase-client
Version: 0.1.1
Summary: The command line client for csvbase
Home-page: https://github.com/calpaterson/csvbase-client
Author: Cal Paterson
Author-email: cal@calpaterson.com
Project-URL: Bug Tracker, https://github.com/calpaterson/csvbase-client/issues
Project-URL: Documentation, https://github.com/calpaterson/csvbase-client/wiki
Project-URL: Source Code, https://github.com/calpaterson/csvbase-client
Project-URL: Changelog, https://github.com/calpaterson/csvbase-client/blob/main/CHANGELOG.md
Keywords: csv data processing
Classifier: Development Status :: 3 - Alpha
Classifier: Intended Audience :: Developers
Classifier: License :: OSI Approved :: GNU Affero General Public License v3 or later (AGPLv3+)
Classifier: Programming Language :: Python :: 3
Classifier: Programming Language :: Python :: 3.8
Classifier: Programming Language :: Python :: 3.9
Classifier: Programming Language :: Python :: 3.10
Classifier: Programming Language :: Python :: 3.11
Classifier: Programming Language :: Python :: 3.12
Classifier: Topic :: Utilities
License-File: COPYING
Requires-Dist: click
Requires-Dist: platformdirs
Requires-Dist: pyappcache >=0.10.0
Requires-Dist: requests
Requires-Dist: toml
Requires-Dist: importlib-resources
Requires-Dist: fsspec
Requires-Dist: rich
Requires-Dist: humanize
